MANIFEST.in
setup.py
palp/.gitignore
palp/README.md
palp/VERSION
palp/__init__.py
palp/conn.py
palp/exception.py
palp/requirements.txt
palp/settings.py
palp.egg-info/PKG-INFO
palp.egg-info/SOURCES.txt
palp.egg-info/dependency_links.txt
palp.egg-info/entry_points.txt
palp.egg-info/requires.txt
palp.egg-info/top_level.txt
palp/controller/__init__.py
palp/controller/controller_item.py
palp/controller/controller_spider.py
palp/controller/controller_spider_jump.py
palp/decorator/__init__.py
palp/decorator/decorator_lock.py
palp/decorator/decorator_run_func_by_thread.py
palp/decorator/decorator_spider_middleware.py
palp/decorator/decorator_spider_once.py
palp/decorator/decorator_spider_wait.py
palp/filter/__init__.py
palp/filter/filter.py
palp/filter/filter_bloom.py
palp/filter/filter_redis_bloom.py
palp/filter/filter_redis_set.py
palp/filter/filter_set.py
palp/item/__init__.py
palp/item/item.py
palp/item/item_lazy.py
palp/item/item_strict.py
palp/middleware/__init__.py
palp/middleware/middleware_cycle_spider_record.py
palp/middleware/middleware_request.py
palp/middleware/middleware_request_check.py
palp/middleware/middleware_request_filter.py
palp/middleware/middleware_request_record.py
palp/middleware/middleware_request_recycle.py
palp/middleware/middleware_spider.py
palp/middleware/middleware_spider_end.py
palp/middleware/middleware_spider_recycle.py
palp/network/__init__.py
palp/network/downloader.py
palp/network/downloader_httpx.py
palp/network/downloader_requests.py
palp/network/request.py
palp/network/request_method.py
palp/network/response.py
palp/network/response_httpx.py
palp/network/response_requests.py
palp/pipeline/__init__.py
palp/pipeline/pipeline.py
palp/pipeline/pipeline_filter.py
palp/pipeline/pipeline_recycle.py
palp/sequence/__init__.py
palp/sequence/sequence.py
palp/sequence/sequence_memory.py
palp/sequence/sequence_redis_borrow.py
palp/sequence/sequence_redis_item.py
palp/sequence/sequence_redis_request.py
palp/spider/__init__.py
palp/spider/spider.py
palp/spider/spider_cycle.py
palp/spider/spider_distributive.py
palp/spider/spider_jump.py
palp/spider/spider_local.py
palp/template/item/item.tmpl
