Metadata-Version: 2.1
Name: palp
Version: 0.0.191
Summary: 一个 爬虫框架
Home-page: https://github.com/Leviathangk/palp
Author: 郭一会儿
Author-email: 1015295213@qq.com
License: MIT Licence
Keywords: palp,scrapy,feapder
Platform: any
